{
    "classname": "mainContainer",
    "definitions": {
        "apis": {
            "custom": [
                {
                    "group": "General",
                    "kuid": "f5cdd3c724ad434fab44821691eb880e",
                    "paramList": [
                        {
                            "name": "menuNumber"
                        }
                    ],
                    "propertyKey": "setActiveFooterMenu",
                    "pw": {
                        "displayName": "setActiveFooterMenu",
                        "uiRepresentation": "Label-Label-Button-Button"
                    },
                    "srcWgtKUID": "ab939ca6b6224596b8d6345d4b83877f",
                    "type": "event"
                }
            ],
            "passthrough": [
                {
                    "access": "Enable",
                    "group": "General",
                    "kuid": "e87f7d873eea43ab87599c928c830bfe",
                    "originalPropertyKey": "setVisibility",
                    "propertyKey": "setFooterVisibility",
                    "pw": {
                        "access": "readwrite",
                        "category": "action",
                        "displayName": "setFooterVisibility",
                        "srcWidget": "flxFooter",
                        "type": "action",
                        "uiRepresentation": "Label-Label-Button-Button",
                        "wType": "FlexContainer"
                    },
                    "srcWgtKUID": "g8bde1fbf7e3485d92e81a98ca089bf0"
                }
            ]
        },
        "events": {
            "custom": [],
            "passthrough": [
                {
                    "access": "Enable",
                    "group": "General",
                    "kuid": "g3dde833386e4fb69b919dff36316576",
                    "originalPropertyKey": "onClick",
                    "propertyIndex": 1,
                    "propertyKey": "onFooterLeftClick",
                    "pw": {
                        "access": "readwrite",
                        "category": "action",
                        "displayName": "onFooterLeftClick",
                        "srcWidget": "flxFooterLeft",
                        "type": "action",
                        "uiRepresentation": "Label-Label-Button-Button",
                        "wType": "FlexContainer"
                    },
                    "srcWgtKUID": "edc358d5472f44e4b258032e1715a1c4"
                },
                {
                    "access": "Enable",
                    "group": "General",
                    "kuid": "f602af7a613f4eea98235d8dc04f3fca",
                    "originalPropertyKey": "onClick",
                    "propertyIndex": 2,
                    "propertyKey": "onFooterCenterClick",
                    "pw": {
                        "access": "readwrite",
                        "category": "action",
                        "displayName": "onFooterCenterClick",
                        "srcWidget": "flxFooterCenter",
                        "type": "action",
                        "uiRepresentation": "Label-Label-Button-Button",
                        "wType": "FlexContainer"
                    },
                    "srcWgtKUID": "d4d5a5ae77cc46aa8f7bac950ff9f252"
                },
                {
                    "access": "Enable",
                    "group": "General",
                    "kuid": "a9e8b7450a5b4177b57d17d26d1beae3",
                    "originalPropertyKey": "onClick",
                    "propertyIndex": 3,
                    "propertyKey": "onFooterRightClick",
                    "pw": {
                        "access": "readwrite",
                        "category": "action",
                        "displayName": "onFooterRightClick",
                        "srcWidget": "flxFooterRight",
                        "type": "action",
                        "uiRepresentation": "Label-Label-Button-Button",
                        "wType": "FlexContainer"
                    },
                    "srcWgtKUID": "bfc9fdbd6a31451a96a50937fa230350"
                }
            ]
        },
        "groups": {
            "apis": [
                "General"
            ],
            "events": [],
            "properties": [],
            "widgets": []
        },
        "properties": {
            "custom": [],
            "passthrough": []
        },
        "widgets": {
            "expose": [],
            "passthrough": []
        }
    },
    "namespace": "com.qualifacts",
    "version": "1.0.0"
}